src/__init__.py
src/logic.py
src/main.py
project_name_0.0.0-0.0.3.dist-info/METADATA
project_name_0.0.0-0.0.3.dist-info/WHEEL
project_name_0.0.0-0.0.3.dist-info/entry_points.txt
project_name_0.0.0-0.0.3.dist-info/top_level.txt
project_name_0.0.0-0.0.3.dist-info/RECORD
